[{"eventId": 80112, "status": 5, "statusId": 10}, {"eventId": 80112, "status": 4, "statusId": 20}, {"eventId": 80112, "status": 6, "statusId": 30}, {"eventId": 80112, "status": 7, "statusId": 40}, {"eventId": 80112, "status": 9, "statusId": 50}, {"eventId": 80112, "status": 8, "statusId": 60}, {"eventId": 80112, "status": 10, "statusId": 70}, {"eventId": 80112, "status": 11, "statusId": 80}, {"eventId": 80112, "status": 17, "statusId": 90}, {"eventId": 80112, "status": 16, "statusId": 100}, {"eventId": 80112, "status": 18, "statusId": 110}, {"eventId": 80112, "status": 19, "statusId": 120}, {"eventId": 80112, "status": 33, "statusId": 130}, {"eventId": 80112, "status": 32, "statusId": 140}, {"eventId": 80112, "status": 34, "statusId": 150}, {"eventId": 80112, "status": 35, "statusId": 160}, {"eventId": 80112, "status": 65, "statusId": 170}, {"eventId": 80112, "status": 64, "statusId": 180}, {"eventId": 80112, "status": 66, "statusId": 190}, {"eventId": 80112, "status": 67, "statusId": 200}, {"eventId": 80112, "status": 129, "statusId": 210}, {"eventId": 80112, "status": 128, "statusId": 220}, {"eventId": 80112, "status": 130, "statusId": 230}, {"eventId": 80112, "status": 131, "statusId": 240}, {"eventId": 80112, "status": 257, "statusId": 250}, {"eventId": 80112, "status": 257, "statusId": 260}, {"eventId": 80112, "status": 257, "statusId": 270}, {"eventId": 80112, "status": 257, "statusId": 280}, {"eventId": 80112, "status": 259, "statusId": 290}]